{
  "posts": [
    {
      "id": 1,
      "title": "json-server",
      "author": "typicode"
    }
  ],
  "comments": [
    {
      "id": 1,
      "body": "some comment",
      "postId": 1
    }
  ],
  "profile": {
    "name": "typicode"
  },
  "foods": [
    {
      "name": "Apple",
      "quantity": "5",
      "minQuantity": "2",
      "type": "fruit",
      "id": 1
    },
    {
      "name": "Steak",
      "quantity": "2",
      "minQuantity": "2",
      "type": "meat",
      "id": 2
    },
    {
      "name": "Fish",
      "quantity": "01",
      "minQuantity": "01",
      "type": "meat",
      "id": 3
    }
  ],
  "foodType": [
    {
      "id": 1,
      "name": "Vegetable",
      "value": "vegetable"
    },
    {
      "id": 2,
      "name": "Meat",
      "value": "meat"
    },
    {
      "id": 3,
      "name": "Fruit",
      "value": "fruit"
    }
  ]
}